func_python/README.md
func_python/__init__.py
func_python/cloudevent.py
func_python/http.py
func_python-0.7.0.dist-info/METADATA
func_python-0.7.0.dist-info/WHEEL
func_python-0.7.0.dist-info/licenses/LICENSE
func_python-0.7.0.dist-info/RECORD
