Metadata-Version: 2.4
Name: func-python
Version: 0.7.0
Summary: Knative Functions Python Middleware
License: Apache-2.0
License-File: LICENSE
Author: The Knative Authors
Author-email: knative-dev@googlegroups.com
Requires-Python: >=3.8,<4.0
Classifier: License :: OSI Approved :: Apache Software License
Classifier: Programming Language :: Python :: 3
Classifier: Programming Language :: Python :: 3.8
Classifier: Programming Language :: Python :: 3.9
Classifier: Programming Language :: Python :: 3.10
Classifier: Programming Language :: Python :: 3.11
Classifier: Programming Language :: Python :: 3.12
Classifier: Programming Language :: Python :: 3.13
Classifier: Programming Language :: Python :: 3.14
Requires-Dist: cloudevents (>=1.11.0,<2.0.0)
Requires-Dist: hypercorn (>=0.17.3,<0.18.0)
Project-URL: Repository, https://github.com/knative-extensions/func-python
